src/__init__.py
src/registrycleaner.py
registrycleaner-0.0.2.dist-info/LICENSE
registrycleaner-0.0.2.dist-info/METADATA
registrycleaner-0.0.2.dist-info/WHEEL
registrycleaner-0.0.2.dist-info/entry_points.txt
registrycleaner-0.0.2.dist-info/top_level.txt
registrycleaner-0.0.2.dist-info/RECORD
