Metadata-Version: 2.1
Name: registrycleaner
Version: 0.0.2
Summary: A pip package for deleting tag in private docker registry
Home-page: https://github.com/alegraio/registry-cleaner
Author: Ali YILDIZ
Author-email: ali.yildiz@alegradigital.com
Maintainer: Ali YILDIZ
License: UNKNOWN
Platform: UNKNOWN
Classifier: Programming Language :: Python :: 3
Classifier: License :: OSI Approved :: MIT License
Classifier: Operating System :: OS Independent
Requires-Python: >=3.6
Requires-Dist: requests (>=2.22.0)
Requires-Dist: argparse (>=1.4.0)
